modular_provider_architecture_definition/__init__.py
modular_provider_architecture_definition/definition.py
modular_provider_architecture_definition/validators.py
modular_provider_architecture_definition-0.1.4.dist-info/METADATA
modular_provider_architecture_definition-0.1.4.dist-info/WHEEL
modular_provider_architecture_definition-0.1.4.dist-info/namespace_packages.txt
modular_provider_architecture_definition-0.1.4.dist-info/top_level.txt
modular_provider_architecture_definition-0.1.4.dist-info/RECORD
