Metadata-Version: 2.1
Name: modular-provider-architecture-definition
Version: 0.1.4
Summary: An example distribution built with Pants.
Home-page: UNKNOWN
Author: Pantsbuild
License: UNKNOWN
Platform: UNKNOWN
Classifier: Programming Language :: Python :: 3.7
Requires-Dist: astroid (<3.0.0,>=2.5.8)
Requires-Dist: python-architecture-linter (==0.1.4)
